CHANGELOG.md
LICENSE
README.md
pyproject.toml
artificial_artwork/__init__.py
artificial_artwork/__version__.py
artificial_artwork/_demo.py
artificial_artwork/_logging.py
artificial_artwork/_logging_config.py
artificial_artwork/_main.py
artificial_artwork/algorithm.py
artificial_artwork/cli.py
artificial_artwork/cmd_demo.py
artificial_artwork/cost_computer.py
artificial_artwork/disk_interface.py
artificial_artwork/disk_operations.py
artificial_artwork/image/__init__.py
artificial_artwork/image/image.py
artificial_artwork/image/image_factory.py
artificial_artwork/image/image_operations.py
artificial_artwork/image/image_processor.py
artificial_artwork/nst_image.py
artificial_artwork/nst_math.py
artificial_artwork/nst_tf_algorithm.py
artificial_artwork/pre_trained_models/__init__.py
artificial_artwork/pre_trained_models/vgg.py
artificial_artwork/pretrained_model/__init__.py
artificial_artwork/pretrained_model/layers_getter.py
artificial_artwork/pretrained_model/model_handler.py
artificial_artwork/pretrained_model/model_handler_interface.py
artificial_artwork/pretrained_model/model_routines.py
artificial_artwork/production_networks/__init__.py
artificial_artwork/production_networks/image_model.py
artificial_artwork/production_networks/style_layer_selector.py
artificial_artwork/style_model/__init__.py
artificial_artwork/style_model/graph_builder.py
artificial_artwork/style_model/graph_factory.py
artificial_artwork/styling_observer.py
artificial_artwork/termination_condition/__init__.py
artificial_artwork/termination_condition/termination_condition.py
artificial_artwork/termination_condition/termination_condition_interface.py
artificial_artwork/termination_condition_adapter.py
artificial_artwork/termination_condition_adapter_factory.py
artificial_artwork/tf_session_runner.py
artificial_artwork/utils.py
artificial_artwork-2.0.0.dist-info/LICENSE
artificial_artwork-2.0.0.dist-info/METADATA
artificial_artwork-2.0.0.dist-info/WHEEL
artificial_artwork-2.0.0.dist-info/entry_points.txt
artificial_artwork-2.0.0.dist-info/RECORD
