Metadata-Version: 2.1
Name: artificial-artwork
Version: 2.0.0
Summary: Create artificial artwork by transfering the appearance of one image (eg a famous painting) to another user-supplied image (eg your favourite photograph).
Home-page: https://github.com/boromir674/neural-style-transfer
License: AGPL-3.0-only
Keywords: artificial intelligence,neural style transfer,artificial art,deep learning,cli,gui
Author: Konstantinos Lampridis
Author-email: k.lampridis@hotmail.com
Maintainer: Konstantinos Lampridis
Maintainer-email: k.lampridis@hotmail.com
Requires-Python: >=3.10,<3.12
Classifier: Development Status :: 5 - Production/Stable
Classifier: Intended Audience :: Developers
Classifier: Intended Audience :: End Users/Desktop
Classifier: Intended Audience :: Science/Research
Classifier: License :: OSI Approved :: GNU Affero General Public License v3
Classifier: Natural Language :: English
Classifier: Operating System :: MacOS
Classifier: Operating System :: POSIX :: Linux
Classifier: Operating System :: Unix
Classifier: Programming Language :: Python
Classifier: Programming Language :: Python :: 3
Classifier: Programming Language :: Python :: 3.10
Classifier: Programming Language :: Python :: 3.11
Classifier: Programming Language :: Python :: 3.8
Classifier: Programming Language :: Python :: 3.9
Classifier: Topic :: Artistic Software
Classifier: Topic :: Scientific/Engineering :: Artificial Intelligence
Classifier: Topic :: Scientific/Engineering :: Image Processing
Classifier: Topic :: Software Development
Classifier: Topic :: Software Development :: Libraries :: Python Modules
Classifier: Topic :: System :: Software Distribution
Classifier: Typing :: Typed
Provides-Extra: docs
Provides-Extra: gui
Provides-Extra: test
Requires-Dist: attrs (>=23.1.0,<24.0.0)
Requires-Dist: click (>=8.1.7,<9.0.0)
Requires-Dist: cython (>=3.0.2,<4.0.0)
Requires-Dist: griffe (>=1.5.1,<2.0.0) ; extra == "docs"
Requires-Dist: imageio (>=2.10.1,<2.11.0)
Requires-Dist: matplotlib (>=3.7,<3.8) ; extra == "gui"
Requires-Dist: mkdocs (>=1.5.3,<2.0.0) ; extra == "docs"
Requires-Dist: mkdocs-click (>=0.8.1,<0.9.0) ; extra == "docs"
Requires-Dist: mkdocs-gen-files (>=0.5.0,<0.6.0) ; extra == "docs"
Requires-Dist: mkdocs-literate-nav (>=0.6.1,<0.7.0) ; extra == "docs"
Requires-Dist: mkdocs-macros-plugin (>=1.0.5,<2.0.0) ; extra == "docs"
Requires-Dist: mkdocs-material (>=9.4.8,<10.0.0) ; extra == "docs"
Requires-Dist: mkdocs-mermaid2-plugin (>=1.1.1,<2.0.0) ; extra == "docs"
Requires-Dist: mkdocs-section-index (>=0.3.8,<0.4.0) ; extra == "docs"
Requires-Dist: mkdocstrings (>=0.26.2,<0.27.0) ; extra == "docs"
Requires-Dist: mkdocstrings-python (>=1.12.2,<2.0.0) ; extra == "docs"
Requires-Dist: numpy (>=1,<2)
Requires-Dist: protobuf (>=3.19.1,<4.0.0)
Requires-Dist: pymdown-extensions (>=10.4,<11.0) ; extra == "docs"
Requires-Dist: pytest (>=7.4.2,<8.0.0) ; extra == "test"
Requires-Dist: pytest-click (>=1.1.0,<2.0.0) ; extra == "test"
Requires-Dist: pytest-cov (>=4.1.0,<5.0.0) ; extra == "test"
Requires-Dist: pytest-explicit (>=1.0.1,<2.0.0) ; extra == "test"
Requires-Dist: pytest-xdist (>=3.3.1,<4.0.0) ; extra == "test"
Requires-Dist: scipy (>=1.4.1,<2.0.0)
Requires-Dist: software-patterns (>=2.0.0,<3.0.0)
Requires-Dist: tensorflow (>=2.2.0,<3.0.0)
Project-URL: Bug Tracker, https://github.com/boromir674/neural-style-transfer/issues
Project-URL: CI: Github Actions, https://github.com/boromir674/neural-style-transfer/actions
Project-URL: Changelog, https://github.com/boromir674/neural-style-transfer/blob/master/CHANGELOG.rst
Project-URL: Documentation, https://neural-style-transfer.readthedocs.io/
Project-URL: Repository, https://github.com/boromir674/neural-style-transfer
Project-URL: Source Code, https://github.com/boromir674/neural-style-transfer
